[
{"Type_id":301001,"Map_id":301,"Dec_lv":60,"Refresh_time":30,"X":118,"Y":120,"Tire":0,"Sp_drop":[]},
{"Type_id":301002,"Map_id":301,"Dec_lv":60,"Refresh_time":30,"X":119,"Y":183,"Tire":0,"Sp_drop":[]},
{"Type_id":301003,"Map_id":301,"Dec_lv":60,"Refresh_time":30,"X":120,"Y":58,"Tire":0,"Sp_drop":[]},
{"Type_id":301004,"Map_id":301,"Dec_lv":60,"Refresh_time":30,"X":57,"Y":121,"Tire":0,"Sp_drop":[]},
{"Type_id":301005,"Map_id":301,"Dec_lv":60,"Refresh_time":30,"X":242,"Y":120,"Tire":0,"Sp_drop":[]},
{"Type_id":301006,"Map_id":301,"Dec_lv":60,"Refresh_time":30,"X":240,"Y":184,"Tire":0,"Sp_drop":[]},
{"Type_id":301007,"Map_id":301,"Dec_lv":60,"Refresh_time":30,"X":240,"Y":60,"Tire":0,"Sp_drop":[]},
{"Type_id":302001,"Map_id":302,"Dec_lv":60,"Refresh_time":600,"X":118,"Y":120,"Tire":1,"Sp_drop":[]},
{"Type_id":302002,"Map_id":302,"Dec_lv":60,"Refresh_time":600,"X":119,"Y":183,"Tire":1,"Sp_drop":[]},
{"Type_id":302003,"Map_id":302,"Dec_lv":60,"Refresh_time":600,"X":120,"Y":58,"Tire":1,"Sp_drop":[]},
{"Type_id":302004,"Map_id":302,"Dec_lv":60,"Refresh_time":600,"X":57,"Y":121,"Tire":1,"Sp_drop":[]},
{"Type_id":302005,"Map_id":302,"Dec_lv":60,"Refresh_time":600,"X":242,"Y":120,"Tire":1,"Sp_drop":[]},
{"Type_id":302006,"Map_id":302,"Dec_lv":60,"Refresh_time":900,"X":240,"Y":184,"Tire":1,"Sp_drop":[]},
{"Type_id":302007,"Map_id":302,"Dec_lv":60,"Refresh_time":900,"X":240,"Y":60,"Tire":1,"Sp_drop":[]},
{"Type_id":302008,"Map_id":302,"Dec_lv":60,"Refresh_time":900,"X":302,"Y":118,"Tire":1,"Sp_drop":[]},
{"Type_id":303001,"Map_id":303,"Dec_lv":60,"Refresh_time":900,"X":118,"Y":120,"Tire":1,"Sp_drop":[]},
{"Type_id":303002,"Map_id":303,"Dec_lv":60,"Refresh_time":900,"X":119,"Y":183,"Tire":1,"Sp_drop":[]},
{"Type_id":303003,"Map_id":303,"Dec_lv":60,"Refresh_time":900,"X":120,"Y":58,"Tire":1,"Sp_drop":[]},
{"Type_id":303004,"Map_id":303,"Dec_lv":60,"Refresh_time":900,"X":57,"Y":121,"Tire":1,"Sp_drop":[]},
{"Type_id":303005,"Map_id":303,"Dec_lv":60,"Refresh_time":900,"X":242,"Y":120,"Tire":1,"Sp_drop":[]},
{"Type_id":303006,"Map_id":303,"Dec_lv":60,"Refresh_time":900,"X":240,"Y":184,"Tire":1,"Sp_drop":[]},
{"Type_id":303007,"Map_id":303,"Dec_lv":60,"Refresh_time":1200,"X":240,"Y":60,"Tire":1,"Sp_drop":[]},
{"Type_id":303008,"Map_id":303,"Dec_lv":60,"Refresh_time":1200,"X":302,"Y":118,"Tire":1,"Sp_drop":[]},
{"Type_id":304001,"Map_id":304,"Dec_lv":60,"Refresh_time":1200,"X":118,"Y":120,"Tire":1,"Sp_drop":[]},
{"Type_id":304002,"Map_id":304,"Dec_lv":60,"Refresh_time":1200,"X":119,"Y":183,"Tire":1,"Sp_drop":[]},
{"Type_id":304003,"Map_id":304,"Dec_lv":60,"Refresh_time":1200,"X":120,"Y":58,"Tire":1,"Sp_drop":[]},
{"Type_id":304004,"Map_id":304,"Dec_lv":60,"Refresh_time":1200,"X":57,"Y":121,"Tire":1,"Sp_drop":[]},
{"Type_id":304005,"Map_id":304,"Dec_lv":60,"Refresh_time":1200,"X":242,"Y":120,"Tire":1,"Sp_drop":[]},
{"Type_id":304006,"Map_id":304,"Dec_lv":0,"Refresh_time":60,"X":240,"Y":184,"Tire":1,"Sp_drop":[]},
{"Type_id":304007,"Map_id":304,"Dec_lv":0,"Refresh_time":60,"X":240,"Y":60,"Tire":1,"Sp_drop":[]},
{"Type_id":304008,"Map_id":304,"Dec_lv":0,"Refresh_time":60,"X":302,"Y":118,"Tire":1,"Sp_drop":[]},
{"Type_id":305001,"Map_id":305,"Dec_lv":0,"Refresh_time":60,"X":118,"Y":120,"Tire":1,"Sp_drop":[]},
{"Type_id":305002,"Map_id":305,"Dec_lv":0,"Refresh_time":60,"X":119,"Y":183,"Tire":1,"Sp_drop":[]},
{"Type_id":305003,"Map_id":305,"Dec_lv":0,"Refresh_time":60,"X":120,"Y":58,"Tire":1,"Sp_drop":[]},
{"Type_id":305004,"Map_id":305,"Dec_lv":0,"Refresh_time":60,"X":57,"Y":121,"Tire":1,"Sp_drop":[]},
{"Type_id":305005,"Map_id":305,"Dec_lv":0,"Refresh_time":60,"X":242,"Y":120,"Tire":1,"Sp_drop":[]},
{"Type_id":305006,"Map_id":305,"Dec_lv":0,"Refresh_time":60,"X":240,"Y":184,"Tire":1,"Sp_drop":[]},
{"Type_id":305007,"Map_id":305,"Dec_lv":0,"Refresh_time":60,"X":240,"Y":60,"Tire":1,"Sp_drop":[]},
{"Type_id":305008,"Map_id":305,"Dec_lv":0,"Refresh_time":60,"X":302,"Y":118,"Tire":1,"Sp_drop":[]}
]